royalpack/__init__.py
royalpack/__main__.py
royalpack/bolts/__init__.py
royalpack/bolts/login.py
royalpack/bolts/sentry.py
royalpack/bolts/target.py
royalpack/commands/__init__.py
royalpack/commands/ahnonlosoio.py
royalpack/commands/answer.py
royalpack/commands/cat.py
royalpack/commands/ciaoruozi.py
royalpack/commands/color.py
royalpack/commands/cv.py
royalpack/commands/diobot.py
royalpack/commands/dog.py
royalpack/commands/emojify.py
royalpack/commands/fiorygi.py
royalpack/commands/fortune.py
royalpack/commands/hack.py
royalpack/commands/login.py
royalpack/commands/loginprogress.py
royalpack/commands/man.py
royalpack/commands/ping.py
royalpack/commands/pmots.py
royalpack/commands/rocoinflip.py
royalpack/commands/roll.py
royalpack/commands/ship.py
royalpack/commands/smecds.py
royalpack/commands/spell.py
royalpack/commands/version.py
royalpack/commands/whoami.py
royalpack/config.py
royalpack/database/__init__.py
royalpack/database/alembic/README
royalpack/database/alembic/env.py
royalpack/database/alembic/script.py.mako
royalpack/database/alembic/versions/113c2444dad4_make_find_time_nullable.py
royalpack/database/alembic/versions/c6aacbd5d796_first_revision.py
royalpack/database/alembic/versions/e6b0d97063a1_add_timestamp_to_transactions.py
royalpack/database/base.py
royalpack/database/engine.py
royalpack/services/cryptdailies.py
royalpack-6.10.1.dist-info/LICENSE.txt
royalpack-6.10.1.dist-info/METADATA
royalpack-6.10.1.dist-info/WHEEL
royalpack-6.10.1.dist-info/RECORD
