Metadata-Version: 2.1
Name: royalpack
Version: 6.10.1
Summary: Royalnet Commands for the RYG community
Home-page: https://github.com/RYGhub/royalpack
License: AGPL-3.0-or-later
Keywords: royalnet
Author: Stefano Pigozzi
Author-email: me@steffo.eu
Requires-Python: >=3.8,<4.0
Classifier: Development Status :: 3 - Alpha
Classifier: License :: OSI Approved :: GNU Affero General Public License v3 or later (AGPLv3+)
Classifier: Operating System :: OS Independent
Classifier: Programming Language :: Python :: 3
Classifier: Programming Language :: Python :: 3.8
Classifier: Programming Language :: Python :: 3.9
Classifier: Programming Language :: Python :: 3.10
Classifier: Programming Language :: Python :: 3.11
Classifier: Programming Language :: Python :: 3.12
Requires-Dist: SQLAlchemy-Utils (>=0.37.0,<0.38.0)
Requires-Dist: aiohttp (>=3.7.4,<4.0.0)
Requires-Dist: alembic (>=1.5.8,<2.0.0)
Requires-Dist: arrow (>=1.0.3,<2.0.0)
Requires-Dist: async-timeout (>=3.0.1,<4.0.0)
Requires-Dist: coloredlogs (>=15.0,<16.0)
Requires-Dist: colour (>=0.1.5,<0.2.0)
Requires-Dist: psycopg2 (>=2.8.6,<3.0.0)
Requires-Dist: royalnet (>=6.6.0,<6.7.0)
Requires-Dist: royalnet_console (>=6.6.2,<7.0.0)
Requires-Dist: royalnet_discordpy (>=6.6.2,<7.0.0)
Requires-Dist: royalnet_telethon (>=6.6.2,<7.0.0)
Requires-Dist: royalspells (>=3.2,<4.0)
Requires-Dist: sentry-sdk (>=1.0.0,<2.0.0)
Requires-Dist: steam (>=1.2.0,<2.0.0)
Project-URL: Repository, https://github.com/RYGhub/royalpack
